pymyo/__init__.py
pymyo/myo.py
pymyo/py.typed
pymyo/types.py
pymyo-2.2.3.dist-info/LICENSE.txt
pymyo-2.2.3.dist-info/METADATA
pymyo-2.2.3.dist-info/WHEEL
pymyo-2.2.3.dist-info/top_level.txt
pymyo-2.2.3.dist-info/RECORD
