Metadata-Version: 2.1
Name: pymyo
Version: 2.2.3
Summary: Cross-platform Python API to configure or retrieve data from a Thalmic Labs Myo armband through BLE
Author-email: Crimson-Crow <github@crimsoncrow.dev>
Maintainer-email: Crimson-Crow <github@crimsoncrow.dev>
License: MIT License
Project-URL: Homepage, https://github.com/Crimson-Crow/pymyo
Project-URL: Repository, https://github.com/Crimson-Crow/pymyo.git
Project-URL: Issues, https://github.com/Crimson-Crow/pymyo/issues
Keywords: myo,armband,bluetooth,BLE
Classifier: Development Status :: 5 - Production/Stable
Classifier: Framework :: AsyncIO
Classifier: Intended Audience :: Developers
Classifier: Intended Audience :: Science/Research
Classifier: License :: OSI Approved :: MIT License
Classifier: Operating System :: Microsoft :: Windows :: Windows 10
Classifier: Operating System :: POSIX :: Linux
Classifier: Operating System :: MacOS :: MacOS X
Classifier: Operating System :: Android
Classifier: Programming Language :: Python :: 3
Classifier: Programming Language :: Python :: 3.8
Classifier: Programming Language :: Python :: 3.9
Classifier: Programming Language :: Python :: 3.10
Classifier: Programming Language :: Python :: 3.11
Classifier: Programming Language :: Python :: 3.12
Classifier: Programming Language :: Python :: 3 :: Only
Classifier: Topic :: Scientific/Engineering :: Medical Science Apps.
Classifier: Typing :: Typed
Requires-Python: >=3.8
License-File: LICENSE.txt
Requires-Dist: bleak >=0.22.0
Requires-Dist: typing-extensions ~=4.4 ; python_version < "3.10"
